{
	"floor":[
		{	
			"name":"f2",
			"floordes":"超越裸机手感 纤薄透明壳",
			"floorlist":[
					{"list":"OPPO R9"},
					{"list":"移动电源"},
					{"list":"蓝牙耳机"},
					{"list":"手机壳"},
					{"list":"平板电脑"},
					{"list":"手环"},
					{"list":"更多"}

			],
			"leftimg":"../images/ule-img/70e42788c6445f2b_-1x-1.jpg",
			"products" : [
					{"imgurl":"../images/ule-img/882e1294810a29d9_-1x-1.jpg","descript":"魅族 魅蓝Note5 全网通公开版 32GB 移动联通电信4G手机 双卡双待(月光银)","price":"1088.00","delprice":"1198.00"},
					{"imgurl":"../images/ule-img/40bc445dacbe454b_-1x-1.jpg","descript":"乐视（Le）乐Max2（X820) 4+32G 移动联通电信4G手机 双卡双待","price":"1468.00","delprice":"1599.00"},
					{"imgurl":"../images/ule-img/0c99de2e9ada216c_-1x-1.jpg","descript":"VIVO X9全网通 4GB)","price":"2688.00","delprice":"1599.00"},
					{"imgurl":"../images/ule-img/223cc12494941966_-1x-1.jpg","descript":"苹果(APPLE)IPHONE","price":"6288.00","delprice":"2998.00"},
					{"imgurl":"../images/ule-img/8769ed97e4101144_-1x-1.jpg ","descript":"机械战警苹果6/5数据线","price":"19.90","delprice":"59.00"},
					{"imgurl":"../images/ule-img/36a9a144bf4dfeaf_-1x-1.jpg ","descript":"台电t100CE移动电源","price":"59.90","delprice":"299.00"},
					{"imgurl":"../images/ule-img/0f98e0cdb4b5a9c1_-1x-1.jpg ","descript":"华为T1-A21w荣耀畅玩","price":"1099.00","delprice":"1499.00"},
					{"imgurl":"../images/ule-img/3d1403582817494a_-1x-1.jpg ","descript":"苹果APPLE MACBOOK","price":"7838.00","delprice":"8988.00"}
				],
			"right":[
					{"imgurl":"../images/ule-img/19e24a84b2b1e587_p400x400_m.jpg","descript":"双鹿蓝骑士5号电池10粒装 蓝骑士弹性5号10","price":"9.90"},
					{"imgurl":"../images/ule-img/c818d4c94fabade5_p800x800_m.jpg","descript":"啊琪猫蓝牙二甲X1黑色","price":"59.90"},
					{"imgurl":"../images/ule-img/c7442a2ae4ce224e_p800x800_m.jpg","descript":"中兴(ZTE)L788移动/联通2G老人手机","price":"138.90"},
					{"imgurl":"../images/ule-img/24ceafd58042c8a1_p750x751_m.jpg","descript":"中兴(ZTE)L788移动/联通2G老人手机","price":"138.90"},
					{"imgurl":"../images/ule-img/24ceafd58042c8a1_p750x751_m.jpg","descript":"中兴(ZTE)L788移动/联通2G老人手机","price":"138.90"}
			]
		},
		{	
			"name":"f3",
			"floordes":"美的电饭煲 蒸煮烹饪神器",
			"floorlist":[
					{"list":"剃须刀"},
					{"list":"电烤箱"},
					{"list":"空气净化器"},
					{"list":"豆浆机"},
					{"list":"洗衣机"},
					{"list":"煮蛋机"},
					{"list":"更多"}

			],
			"leftimg":"../images/ule-img/3adddb84347dfa02_-1x-1.jpg",
			"products" : [
					{"imgurl":"../images/ule-img/0a4864a27b02bc00_-1x-1.jpg","descript":"ACA/北美电器ABB-W08暖奶瓶","price":"92.00","delprice":"199.00"},
					{"imgurl":"../images/ule-img/4eccb5163047f0ab_-1x-1.jpg","descript":"蓉事达 电活够SK30W双管","price":"100.00","delprice":"229.00"},
					{"imgurl":"../images/ule-img/c7f44668198d5397_-1x-1.jpg","descript":"天际/TONZE电炖锅","price":"288.00","delprice":"339.00"},
					{"imgurl":"../images/ule-img/443096442c6be674_-1x-1.jpg","descript":"包邮 飞科三头浮动剃须刀","price":"79.00","delprice":"138.00"},
					{"imgurl":"../images/ule-img/968a1fe434587aaf_-1x-1.jpg ","descript":"飞科毛球修剪器充电直插式","price":"35.90","delprice":"59.00"},
					{"imgurl":"../images/ule-img/56f49eda3d2297d7_-1x-1.jpg ","descript":"润宝手臂式电子血压计U808B","price":"109.00","delprice":"246.00"},
					{"imgurl":"../images/ule-img/be49a19e76b6527e_-1x-1.jpg ","descript":"郎康 腰部按摩器 甩脂机","price":"109.00","delprice":"255.00"},
					{"imgurl":"../images/ule-img/c89c74da13d3e09f_-1x-1.jpg","descript":"XINGHONG兴红 XH-17D-3J","price":"158.00","delprice":"399.00"}
				],
			"right":[
					{"imgurl":"../images/ule-img/88061049248b2925_p1200x1200_m.jpg","descript":"飞利浦电吹风风机","price":"54.90"},
					{"imgurl":"../images/ule-img/9e18ba24481acc5f_p640x701_m.jpg","descript":"积分-半球电水壶2升","price":"22.00"},
					{"imgurl":"../images/ule-img/9d98c5ee0c74a058_p495x451_m.jpg","descript":"积分-双层蒸蛋锅28cm","price":"30.90"},
					{"imgurl":"../images/ule-img/28e24d76f6ad48f6_p800x800_m.jpg","descript":"积分-双层蒸蛋锅28cm","price":"30.90"},
					{"imgurl":"../images/ule-img/9dcd7af7d24e80a2_p563x460_m.jpg","descript":"积分-双层蒸蛋锅28cm","price":"30.90"}
			]

		},
		{	
			"name":"f4",
			"floordes":"护肤粉底液 自然裸妆 高校保湿",
			"floorlist":[
					{"list":"洗发水"},
					{"list":"卫生巾"},
					{"list":"洗面奶"},
					{"list":"护手霜"},
					{"list":"睫毛膏"},
					{"list":"沐浴露"},
					{"list":"更多"}

			],
			"leftimg":"../images/ule-img/444ca3255dd34aa3_-1x-1.jpg",
			"products" : [
					{"imgurl":"../images/ule-img/ad7fa434b2a95b10_-1x-1.jpg","descript":"ACA/北美电器ABB-W08暖奶瓶","price":"92.00","delprice":"199.00"},
					{"imgurl":"../images/ule-img/24c08bf154209aa0_-1x-1.jpg","descript":"蓉事达 电活够SK30W双管","price":"100.00","delprice":"229.00"},
					{"imgurl":"../images/ule-img/c7f44668198d5397_-1x-1.jpg","descript":"天际/TONZE电炖锅","price":"288.00","delprice":"339.00"},
					{"imgurl":"../images/ule-img/c849bf8c047f824d_-1x-1.jpg","descript":"包邮 飞科三头浮动剃须刀","price":"79.00","delprice":"138.00"},
					{"imgurl":"../images/ule-img/795604e519e3e0f7_-1x-1.jpg ","descript":"飞科毛球修剪器充电直插式","price":"35.90","delprice":"59.00"},
					{"imgurl":"../images/ule-img/cf26caaff241cc88_-1x-1.jpg ","descript":"润宝手臂式电子血压计U808B","price":"109.00","delprice":"246.00"},
					{"imgurl":"../images/ule-img/1aa9a056426baec6_-1x-1.jpg ","descript":"郎康 腰部按摩器 甩脂机","price":"109.00","delprice":"255.00"},
					{"imgurl":"../images/ule-img/c89c74da13d3e09f_-1x-1.jpg","descript":"XINGHONG兴红 XH-17D-3J","price":"158.00","delprice":"399.00"}
				],
			"right":[
					{"imgurl":"../images/ule-img/386843a39f649d9c_-1x-1.jpg","descript":"飞利浦电吹风风机","price":"54.90"},
					{"imgurl":"../images/ule-img/86976f42704e597a_-1x-1.jpg","descript":"积分-半球电水壶2升","price":"22.00"},
					{"imgurl":"../images/ule-img/938a5cac8493eb73_-1x-1.jpg","descript":"积分-双层蒸蛋锅28cm","price":"30.90"},
					{"imgurl":"../images/ule-img/938a5cac8493eb73_-1x-1.jpg","descript":"积分-双层蒸蛋锅28cm","price":"30.90"},
					{"imgurl":"../images/ule-img/938a5cac8493eb73_-1x-1.jpg","descript":"积分-双层蒸蛋锅28cm","price":"30.90"}
			]
		},
		{	
			"name":"f5",
			"floordes":"商场同款 女外套打折热卖",
			"floorlist":[
					{"list":"家具服"},
					{"list":"羽绒服"},
					{"list":"卫衣"},
					{"list":"打底裤袜"},
					{"list":"手链"},
					{"list":"开衫"},
					{"list":"更多"}

			],
			"leftimg":"../images/ule-img/e571848aab0fd7cf_-1x-1.jpg",
			"products" : [
					{"imgurl":"../images/ule-img/28e94975f7874041_-1x-1.jpg","descript":"ACA/北美电器ABB-W08暖奶瓶","price":"92.00","delprice":"199.00"},
					{"imgurl":"../images/ule-img/2e6ad1eb24a85807_-1x-1.jpg","descript":"蓉事达 电活够SK30W双管","price":"100.00","delprice":"229.00"},
					{"imgurl":"../images/ule-img/3ae15d1d16b28f0a_-1x-1.jpg","descript":"天际/TONZE电炖锅","price":"288.00","delprice":"339.00"},
					{"imgurl":"../images/ule-img/3bb83496a643dc87_-1x-1.jpg","descript":"包邮 飞科三头浮动剃须刀","price":"79.00","delprice":"138.00"},
					{"imgurl":"../images/ule-img/c3c4d43c0ab7bdea_-1x-1.jpg ","descript":"飞科毛球修剪器充电直插式","price":"35.90","delprice":"59.00"},
					{"imgurl":"../images/ule-img/daa3fc284f9d9ac1_-1x-1.jpg ","descript":"润宝手臂式电子血压计U808B","price":"109.00","delprice":"246.00"},
					{"imgurl":"../images/ule-img/e7c2a4472392cce9_-1x-1.jpg ","descript":"郎康 腰部按摩器 甩脂机","price":"109.00","delprice":"255.00"},
					{"imgurl":"../images/ule-img/c89c74da13d3e09f_-1x-1.jpg","descript":"XINGHONG兴红 XH-17D-3J","price":"158.00","delprice":"399.00"}
				],
			"right":[
					{"imgurl":"../images/ule-img/2c24cbcb118d2be4_p800x800_m.jpg","descript":"2条状，冬季抗冷保暖裤女","price":"54.90"},
					{"imgurl":"../images/ule-img/3563f1693624181a_p790x790_m.jpg","descript":"9.9包邮男士富字吉祥红色平角裤","price":"9.90"},
					{"imgurl":"../images/ule-img/6dc13494624ecf95_p659x633_m.jpg","descript":"时尚情侣披肩 棉麻围巾2016年经典款","price":"3.90"},
					{"imgurl":"../images/ule-img/6dc13494624ecf95_p659x633_m.jpg","descript":"时尚情侣披肩 棉麻围巾2016年经典款","price":"3.90"},
					{"imgurl":"../images/ule-img/6dc13494624ecf95_p659x633_m.jpg","descript":"时尚情侣披肩 棉麻围巾2016年经典款","price":"3.90"}
			],
			"advert":"../images/ule-img/56361116564060bf_-1x-1.jpg"
		},
		{	
			"name":"f6",
			"floordes":"休息百搭 T恤块时尚",
			"floorlist":[
					{"list":"保暖内衣"},
					{"list":"大衣"},
					{"list":"男士内裤"},
					{"list":"牛仔裤"},
					{"list":"西装"},
					{"list":"真皮皮带"},
					{"list":"更多"}

			],
			"leftimg":"../images/ule-img/6993b2445c2946d2_-1x-1.jpg",
			"products" : [
					{"imgurl":"../images/ule-img/0bcabddf509d13d7_-1x-1.jpg","descript":"ACA/北美电器ABB-W08暖奶瓶","price":"92.00","delprice":"199.00"},
					{"imgurl":"../images/ule-img/78aa65ee7427d812_-1x-1.jpg","descript":"蓉事达 电活够SK30W双管","price":"100.00","delprice":"229.00"},
					{"imgurl":"../images/ule-img/8a903a80f84078e7_-1x-1.jpg","descript":"天际/TONZE电炖锅","price":"288.00","delprice":"339.00"},
					{"imgurl":"../images/ule-img/64bed9463ecfc055_-1x-1.jpg","descript":"包邮 飞科三头浮动剃须刀","price":"79.00","delprice":"138.00"},
					{"imgurl":"../images/ule-img/cb91f7ba5a056959_-1x-1.jpg","descript":"飞科毛球修剪器充电直插式","price":"35.90","delprice":"59.00"},
					{"imgurl":"../images/ule-img/2e191949c989dfdd_-1x-1.jpg","descript":"润宝手臂式电子血压计U808B","price":"109.00","delprice":"246.00"},
					{"imgurl":"../images/ule-img/94704a7bf8e57540_-1x-1.jpg ","descript":"郎康 腰部按摩器 甩脂机","price":"109.00","delprice":"255.00"},
					{"imgurl":"../images/ule-img/64bed9463ecfc055_-1x-1.jpg","descript":"XINGHONG兴红 XH-17D-3J","price":"158.00","delprice":"399.00"}
				],
			"right":[
					{"imgurl":"../images/ule-img/234e0e81ac34a72b_p790x790_m.jpg","descript":"2条状，冬季抗冷保暖裤女","price":"54.90"},
					{"imgurl":"../images/ule-img/2f89a2744d4ac60c_p800x800_m.jpg","descript":"9.9包邮男士富字吉祥红色平角裤","price":"9.90"},
					{"imgurl":"../images/ule-img/2f5bf8e6a564824b_p800x800_m.jpg","descript":"时尚情侣披肩 棉麻围巾2016年经典款","price":"3.90"},
					{"imgurl":"../images/ule-img/2f5bf8e6a564824b_p800x800_m.jpg","descript":"时尚情侣披肩 棉麻围巾2016年经典款","price":"3.90"},
					{"imgurl":"../images/ule-img/2f5bf8e6a564824b_p800x800_m.jpg","descript":"时尚情侣披肩 棉麻围巾2016年经典款","price":"3.90"}			],
			"advert":""

		},
			{	
			"name":"f7",
			"floordes":"热门品牌 双肩包时尚潮单",
			"floorlist":[
					{"list":"双肩包"},
					{"list":"拉杆箱"},
					{"list":"新款钱包"},
					{"list":"雪地靴"},
					{"list":"男靴"},
					{"list":"军鞋"},
					{"list":"更多"}

			],
			"leftimg":"../images/ule-img/84e52a2fa0bbe406_-1x-1.jpg",
			"products" : [
					{"imgurl":"../images/ule-img/b238e6fe6f6e44d8_-1x-1.jpg","descript":"ACA/北美电器ABB-W08暖奶瓶","price":"92.00","delprice":"199.00"},
					{"imgurl":"../images/ule-img/012441ea8fc86bf0_-1x-1.jpg","descript":"蓉事达 电活够SK30W双管","price":"100.00","delprice":"229.00"},
					{"imgurl":"../images/ule-img/012441ea8fc86bf0_-1x-1.jpg","descript":"天际/TONZE电炖锅","price":"288.00","delprice":"339.00"},
					{"imgurl":"../images/ule-img/434046d54fef8991_-1x-1.jpg","descript":"包邮 飞科三头浮动剃须刀","price":"79.00","delprice":"138.00"},
					{"imgurl":"../images/ule-img/cb91f7ba5a056959_-1x-1.jpg","descript":"飞科毛球修剪器充电直插式","price":"35.90","delprice":"59.00"},
					{"imgurl":"../images/ule-img/e58f57fb10242168_-1x-1.jpg","descript":"润宝手臂式电子血压计U808B","price":"109.00","delprice":"246.00"},
					{"imgurl":"../images/ule-img/4783b92744ac0721_-1x-1.jpg ","descript":"郎康 腰部按摩器 甩脂机","price":"109.00","delprice":"255.00"},
					{"imgurl":"../images/ule-img/64bed9463ecfc055_-1x-1.jpg","descript":"XINGHONG兴红 XH-17D-3J","price":"158.00","delprice":"399.00"}
				],
			"right":[
					{"imgurl":"../images/ule-img/b238e6fe6f6e44d8_-1x-1.jpg","descript":"2条状，冬季抗冷保暖裤女","price":"54.90"},
					{"imgurl":"../images/ule-img/4b0abfc411bb14db_-1x-1.jpg","descript":"9.9包邮男士富字吉祥红色平角裤","price":"9.90"},
					{"imgurl":"../images/ule-img/4bf596197c539021_-1x-1.jpg","descript":"时尚情侣披肩 棉麻围巾2016年经典款","price":"3.90"},
					{"imgurl":"../images/ule-img/b238e6fe6f6e44d8_-1x-1.jpg","descript":"时尚情侣披肩 棉麻围巾2016年经典款","price":"3.90"},
					{"imgurl":"../images/ule-img/4bf596197c539021_-1x-1.jpg","descript":"时尚情侣披肩 棉麻围巾2016年经典款","price":"3.90"}			],
			"advert":""

		},
		{	
			"name":"f8",
			"floordes":"婴幼儿奶粉 托起宝宝健康的明天",
			"floorlist":[
					{"list":"宝宝奶粉"},
					{"list":"纸尿裤"},
					{"list":"启智玩具"},
					{"list":"奶嘴"},
					{"list":"儿童润肤霜"},
					{"list":"童鞋"},
					{"list":"更多"}

			],
			"leftimg":"../images/ule-img/8e37bed947664d3a_-1x-1.jpg",
			"products" : [
					{"imgurl":"../images/ule-img/16fb304db1360146_-1x-1.jpg","descript":"ACA/北美电器ABB-W08暖奶瓶","price":"92.00","delprice":"199.00"},
					{"imgurl":"../images/ule-img/7159946aeb6d99af_-1x-1.jpg","descript":"蓉事达 电活够SK30W双管","price":"100.00","delprice":"229.00"},
					{"imgurl":"../images/ule-img/d905b6ca8e85905d_-1x-1.jpg","descript":"天际/TONZE电炖锅","price":"288.00","delprice":"339.00"},
					{"imgurl":"../images/ule-img/fef3ea14e1bb24e5_-1x-1.jpg","descript":"包邮 飞科三头浮动剃须刀","price":"79.00","delprice":"138.00"},
					{"imgurl":"../images/ule-img/d2281c28a48d9b33_-1x-1.jpg","descript":"飞科毛球修剪器充电直插式","price":"35.90","delprice":"59.00"},
					{"imgurl":"../images/ule-img/b1a8924eeba82cd3_-1x-1.jpg","descript":"润宝手臂式电子血压计U808B","price":"109.00","delprice":"246.00"},
					{"imgurl":"../images/ule-img/cd234603982eb0db_-1x-1.jpg ","descript":"郎康 腰部按摩器 甩脂机","price":"109.00","delprice":"255.00"},
					{"imgurl":"../images/ule-img/12a0cb134624b3f2_-1x-1.jpg","descript":"XINGHONG兴红 XH-17D-3J","price":"158.00","delprice":"399.00"}
				],
			"right":[
					{"imgurl":"../images/ule-img/ee6a1c015e8628f1_p800x800_m.jpg","descript":"2条状，冬季抗冷保暖裤女","price":"54.90"},
					{"imgurl":"../images/ule-img/9db0718ed4fdd9be_p800x800_m.jpg","descript":"9.9包邮男士富字吉祥红色平角裤","price":"9.90"},
					{"imgurl":"../images/ule-img/4c80981df55247c0_p800x800_m.jpg","descript":"时尚情侣披肩 棉麻围巾2016年经典款","price":"3.90"},
					{"imgurl":"../images/ule-img/ed92a60be56ff9e6_p800x800_m.jpg","descript":"时尚情侣披肩 棉麻围巾2016年经典款","price":"3.90"},
					{"imgurl":"../images/ule-img/20fa4404fe394589_p790x790_m.jpg","descript":"时尚情侣披肩 棉麻围巾2016年经典款","price":"3.90"}			],
			"advert":""

		},
		{	
			"name":"f9",
			"floordes":"热门品牌 双肩包时尚潮单",
			"floorlist":[
					{"list":"双肩包"},
					{"list":"拉杆箱"},
					{"list":"新款钱包"},
					{"list":"雪地靴"},
					{"list":"男靴"},
					{"list":"军鞋"},
					{"list":"更多"}

			],
			"leftimg":"../images/ule-img/a5f843b3baf22e6e_-1x-1.jpg",
			"products" : [
					{"imgurl":"../images/ule-img/1d045f4aed528ed0_-1x-1.jpg","descript":"零听热度佳保暖加长护膝貂绒护膝盖护腿加长加厚男女士","price":"19.00","delprice":"139.00"},
					{"imgurl":"../images/ule-img/ba7afca92f0feb52_-1x-1.jpg","descript":"品尼又 双盘丽水碗架 多功能碗碟刀叉彩板厨房收纳置物架","price":"69.00","delprice":"99.00"},
					{"imgurl":"../images/ule-img/e340a379b68b4b95_-1x-1.jpg","descript":"思思风尚 费格罗条纹拖鞋 红色条纹36-38 蓝色条纹","price":"29.00","delprice":"59.00"},
					{"imgurl":"../images/ule-img/eab4b4cabb6c4ad6_-1x-1.jpg","descript":"新包装随机发货 雕牌健康除菌洗衣液2.5kg杀菌","price":"79.00","delprice":"138.00"}
				],
			"right":[
					{"imgurl":"../images/ule-img/49c360762474445b_-1x-1.jpg","descript":"描眉152一次性纸杯加厚240ML100只","price":"27.90"},
					{"imgurl":"../images/ule-img/31db545ddba0fa21_-1x-1.jpg","descript":"垃圾袋自动收口 家用","price":"39.90"}
				],
			"advert":""

		},
		{	
			"name":"f10",
			"floordes":"跑步鞋品牌当季上新",
			"floorlist":[
					{"list":"冲锋衣"},
					{"list":"登山衣"},
					{"list":"睡袋"},
					{"list":"踏步机"},
					{"list":"乒乓球"},
					{"list":"登山包"},
					{"list":"更多"}

			],
			"leftimg":"../images/ule-img/0ab17adbf23a4725_-1x-1.jpg",
			"products" : [
					{"imgurl":"../images/ule-img/60f598381441d94a_-1x-1.jpg","descript":"包邮李宁2016新款男装训练系列平口开衫无帽卫衣套装","price":"292.00","delprice":"399.00"},
					{"imgurl":"../images/ule-img/6e2a44cda8084974_-1x-1.jpg","descript":"TRAVEL PLUE 2016正品大容量可折叠运动旅行袋","price":"186.00","delprice":"229.00"},
					{"imgurl":"../images/ule-img/283dd47ad73a3abe_-1x-1.jpg","descript":"创悦 加厚绒面双层防潮野餐垫CY-5826四色可选","price":"29.00","delprice":"99.00"},
					{"imgurl":"../images/ule-img/e8ce405c8475792d_-1x-1.jpg","descript":"包邮 飞科三头浮动剃须刀","price":"239.00","delprice":"299.00"}
			],
			"right":[
					{"imgurl":"../images/ule-img/b238e6fe6f6e44d8_-1x-1.jpg","descript":"金字号Q55高清1080p广角迷你车载记录仪","price":"199.90"},
					{"imgurl":"../images/ule-img/4b0abfc411bb14db_-1x-1.jpg","descript":"PAPAGO Gosafe118行车记录仪 高清夜视","price":"279.90"}
			],
			"advert":""

		},
		{	
			"name":"f11",
			"floordes":"进口好货 饼干全球爆款",
			"floorlist":[
					{"list":"乐事薯片"},
					{"list":"坚果"},
					{"list":"奶茶"},
					{"list":"方便面"},
					{"list":"葡萄酒"},
					{"list":"进口零食"},
					{"list":"更多"}

			],
			"leftimg":"../images/ule-img/d8c6a6f0dc489795_-1x-1.jpg",
			"products" : [
					{"imgurl":"../images/ule-img/d841acc8babe4ba2_-1x-1.jpg","descript":"7折钮峰宝 Natures Buzz ACTIVE10马奴卡蜂蜜2瓶装","price":"384.00","delprice":"684.00"},
					{"imgurl":"../images/ule-img/6c0a6241a885449c_-1x-1.jpg","descript":"韩国好丽友扁桃仁90g奶油味喜糖年货韩国井口零食","price":"24.00","delprice":"30.00"},
					{"imgurl":"../images/ule-img/23323669d6349cd9_-1x-1.jpg","descript":"俄罗斯进口玛克法面粉高劲无添加 做面包饺子首选2袋包邮","price":"45.00","delprice":"74.00"},
					{"imgurl":"../images/ule-img/e8b8b264a281c4a7_-1x-1.jpg","descript":"韩国进口石榴汁 海太果汁饮料182ml*15听装","price":"79.00","delprice":"138.00"}
					
				],
			"right":[
					{"imgurl":"../images/ule-img/f4f77a330056d698_-1x-1.jpg","descript":"2条状，冬季抗冷保暖裤女","price":"54.90"},
					{"imgurl":"../images/ule-img/34d94ba2950cbf7b_-1x-1.jpg","descript":"9.9包邮男士富字吉祥红色平角裤","price":"9.90"}
				],
			"advert":""

		}
	]
	
}